diskest/__init__.py
diskest/_version.py
diskest/main.py
diskest/cli/__init__.py
diskest/cli/commands.py
diskest/cli/handlers.py
diskest/core/__init__.py
diskest/core/hardware_detection.py
diskest/core/result_processor.py
diskest/core/system_info.py
diskest/core/test_runner.py
diskest/data/default_config.yaml
diskest/tests/__init__.py
diskest/tests/base_test.py
diskest/tests/fio_test.py
diskest/tests/sysbench_test.py
diskest/utils/__init__.py
diskest/utils/config.py
diskest/utils/database.py
diskest/utils/logging.py
diskest-0.1.0.dist-info/LICENSE
diskest-0.1.0.dist-info/METADATA
diskest-0.1.0.dist-info/WHEEL
diskest-0.1.0.dist-info/entry_points.txt
diskest-0.1.0.dist-info/top_level.txt
diskest-0.1.0.dist-info/RECORD
