Metadata-Version: 2.1
Name: diskest
Version: 0.1.0
Summary: Advanced Disk Benchmark Tool
Author-email: lemonsterfy <lemonsterfy@gmail.com>
License: MIT
Project-URL: Homepage, https://github.com/lemonsterfy/diskest
Project-URL: Repository, https://github.com/lemonsterfy/diskest.git
Classifier: Development Status :: 3 - Alpha
Classifier: Intended Audience :: System Administrators
Classifier: License :: OSI Approved :: MIT License
Classifier: Operating System :: POSIX :: Linux
Classifier: Programming Language :: Python :: 3
Classifier: Programming Language :: Python :: 3.7
Classifier: Programming Language :: Python :: 3.8
Classifier: Programming Language :: Python :: 3.9
Classifier: Programming Language :: Python :: 3.10
Classifier: Programming Language :: Python :: 3.11
Classifier: Programming Language :: Python :: 3.12
Requires-Python: >=3.7
License-File: LICENSE
Requires-Dist: click==8.1.7
Requires-Dist: distro==1.9.0
Requires-Dist: rich==13.9.2
Requires-Dist: pyyaml==6.0.2
Requires-Dist: psutil==6.0.0
Requires-Dist: reportlab==4.2.5
Provides-Extra: dev
Requires-Dist: pytest==8.3.3; extra == "dev"
Requires-Dist: pytest-cov==5.0.0; extra == "dev"
Requires-Dist: pytest-mock==3.14.0; extra == "dev"
Requires-Dist: black==24.10.0; extra == "dev"
Requires-Dist: flake8==7.1.1; extra == "dev"
